langgraph_sdk/__init__.py
langgraph_sdk/client.py
langgraph_sdk/py.typed
langgraph_sdk/schema.py
gigagraph_sdk-0.1.29.dist-info/LICENSE
gigagraph_sdk-0.1.29.dist-info/METADATA
gigagraph_sdk-0.1.29.dist-info/WHEEL
gigagraph_sdk-0.1.29.dist-info/RECORD
