Metadata-Version: 2.1
Name: gigagraph-sdk
Version: 0.1.29
Summary: SDK for interacting with LangGraph API
Home-page: https://github.com/ai-forever/gigagraph
License: MIT
Requires-Python: >=3.9.0,<4.0.0
Classifier: License :: OSI Approved :: MIT License
Classifier: Programming Language :: Python :: 3
Classifier: Programming Language :: Python :: 3.9
Classifier: Programming Language :: Python :: 3.10
Classifier: Programming Language :: Python :: 3.11
Classifier: Programming Language :: Python :: 3.12
Requires-Dist: httpx (>=0.25.2)
Requires-Dist: httpx-sse (>=0.4.0)
Requires-Dist: orjson (>=3.10.1)
Project-URL: Repository, https://github.com/ai-forever/gigagraph
